[
  {
    "ContainingType": "API.Controllers.AuthenticationController",
    "Method": "Register",
    "RelativePath": "api/auth/register",
    "HttpMethod": "POST",
    "IsController": true,
    "Order": 0,
    "Parameters": [
      {
        "Name": "request",
        "Type": "API.DTOs.Authentication.RegisterRequest",
        "IsRequired": true
      }
    ],
    "ReturnTypes": []
  },
  {
    "ContainingType": "API.Controllers.AuthenticateController",
    "Method": "ChangePassword",
    "RelativePath": "api/authenticate/change-password",
    "HttpMethod": "PUT",
    "IsController": true,
    "Order": 0,
    "Parameters": [
      {
        "Name": "changePassRequest",
        "Type": "API.DTOs.Authentication.ChangePassRequest",
        "IsRequired": true
      }
    ],
    "ReturnTypes": [
      {
        "Type": "API.DTOs.APIresponse\u00601[[System.String, System.Private.CoreLib, Version=8.0.0.0, Culture=neutral, PublicKeyToken=7cec85d7bea7798e]]",
        "MediaTypes": [
          "text/plain",
          "application/json",
          "text/json"
        ],
        "StatusCode": 200
      }
    ]
  },
  {
    "ContainingType": "API.Controllers.AuthenticateController",
    "Method": "GetResetCode",
    "RelativePath": "api/authenticate/forgot-password/{email}",
    "HttpMethod": "GET",
    "IsController": true,
    "Order": 0,
    "Parameters": [
      {
        "Name": "email",
        "Type": "System.String",
        "IsRequired": true
      }
    ],
    "ReturnTypes": [
      {
        "Type": "API.DTOs.APIresponse\u00601[[System.String, System.Private.CoreLib, Version=8.0.0.0, Culture=neutral, PublicKeyToken=7cec85d7bea7798e]]",
        "MediaTypes": [
          "text/plain",
          "application/json",
          "text/json"
        ],
        "StatusCode": 200
      }
    ]
  },
  {
    "ContainingType": "API.Controllers.AuthenticateController",
    "Method": "Login",
    "RelativePath": "api/authenticate/login",
    "HttpMethod": "POST",
    "IsController": true,
    "Order": 0,
    "Parameters": [
      {
        "Name": "request",
        "Type": "API.DTOs.Authentication.AuthenticateLoginRequest",
        "IsRequired": true
      }
    ],
    "ReturnTypes": [
      {
        "Type": "API.DTOs.Authentication.AuthenticationResponse",
        "MediaTypes": [
          "text/plain",
          "application/json",
          "text/json"
        ],
        "StatusCode": 200
      }
    ]
  },
  {
    "ContainingType": "API.Controllers.AuthenticateController",
    "Method": "Logout",
    "RelativePath": "api/authenticate/logout",
    "HttpMethod": "POST",
    "IsController": true,
    "Order": 0,
    "Parameters": [
      {
        "Name": "refreshToken",
        "Type": "API.DTOs.Authentication.RefreshTokenRequest",
        "IsRequired": true
      }
    ],
    "ReturnTypes": []
  },
  {
    "ContainingType": "API.Controllers.AuthenticateController",
    "Method": "ChangePasswordLogged",
    "RelativePath": "api/authenticate/put-password",
    "HttpMethod": "PUT",
    "IsController": true,
    "Order": 0,
    "Parameters": [
      {
        "Name": "rq",
        "Type": "API.DTOs.Authentication.ChangePassLogged",
        "IsRequired": true
      }
    ],
    "ReturnTypes": [
      {
        "Type": "API.DTOs.APIresponse\u00601[[System.String, System.Private.CoreLib, Version=8.0.0.0, Culture=neutral, PublicKeyToken=7cec85d7bea7798e]]",
        "MediaTypes": [
          "text/plain",
          "application/json",
          "text/json"
        ],
        "StatusCode": 200
      }
    ]
  },
  {
    "ContainingType": "API.Controllers.AuthenticateController",
    "Method": "RefreshToken",
    "RelativePath": "api/authenticate/refresh-token",
    "HttpMethod": "POST",
    "IsController": true,
    "Order": 0,
    "Parameters": [
      {
        "Name": "refreshToken",
        "Type": "API.DTOs.Authentication.RefreshTokenRequest",
        "IsRequired": true
      }
    ],
    "ReturnTypes": [
      {
        "Type": "API.DTOs.Authentication.AuthenticationResponse",
        "MediaTypes": [
          "text/plain",
          "application/json",
          "text/json"
        ],
        "StatusCode": 200
      }
    ]
  },
  {
    "ContainingType": "API.Controllers.AuthenticateController",
    "Method": "Register",
    "RelativePath": "api/authenticate/register",
    "HttpMethod": "POST",
    "IsController": true,
    "Order": 0,
    "Parameters": [
      {
        "Name": "request",
        "Type": "API.DTOs.Authentication.RegisterRequest",
        "IsRequired": true
      }
    ],
    "ReturnTypes": [
      {
        "Type": "API.DTOs.APIresponse\u00601[[System.String, System.Private.CoreLib, Version=8.0.0.0, Culture=neutral, PublicKeyToken=7cec85d7bea7798e]]",
        "MediaTypes": [
          "text/plain",
          "application/json",
          "text/json"
        ],
        "StatusCode": 200
      }
    ]
  },
  {
    "ContainingType": "API.Controllers.AuthenticateController",
    "Method": "ValidateCode",
    "RelativePath": "api/authenticate/validate-code/{token}",
    "HttpMethod": "POST",
    "IsController": true,
    "Order": 0,
    "Parameters": [
      {
        "Name": "token",
        "Type": "System.String",
        "IsRequired": true
      },
      {
        "Name": "code",
        "Type": "API.DTOs.Authentication.CodeForgot",
        "IsRequired": true
      }
    ],
    "ReturnTypes": [
      {
        "Type": "API.DTOs.APIresponse\u00601[[System.String, System.Private.CoreLib, Version=8.0.0.0, Culture=neutral, PublicKeyToken=7cec85d7bea7798e]]",
        "MediaTypes": [
          "text/plain",
          "application/json",
          "text/json"
        ],
        "StatusCode": 200
      }
    ]
  },
  {
    "ContainingType": "API.Controllers.EpisodesController",
    "Method": "PostEpisode",
    "RelativePath": "api/Episodes",
    "HttpMethod": "POST",
    "IsController": true,
    "Order": 0,
    "Parameters": [
      {
        "Name": "request",
        "Type": "API.DTOs.Episode.EpisodeCreationRequest",
        "IsRequired": true
      }
    ],
    "ReturnTypes": [
      {
        "Type": "API.DTOs.APIresponse\u00601[[API.DTOs.Episode.EpisodeGeneralReponse, API, Version=1.0.0.0, Culture=neutral, PublicKeyToken=null]]",
        "MediaTypes": [
          "text/plain",
          "application/json",
          "text/json"
        ],
        "StatusCode": 200
      }
    ]
  },
  {
    "ContainingType": "API.Controllers.EpisodesController",
    "Method": "GetEpisode",
    "RelativePath": "api/Episodes/{id}",
    "HttpMethod": "GET",
    "IsController": true,
    "Order": 0,
    "Parameters": [
      {
        "Name": "id",
        "Type": "System.Int32",
        "IsRequired": true
      }
    ],
    "ReturnTypes": [
      {
        "Type": "API.DTOs.APIresponse\u00601[[API.DTOs.Episode.EpisodeGeneralReponse, API, Version=1.0.0.0, Culture=neutral, PublicKeyToken=null]]",
        "MediaTypes": [
          "text/plain",
          "application/json",
          "text/json"
        ],
        "StatusCode": 200
      }
    ]
  },
  {
    "ContainingType": "API.Controllers.EpisodesController",
    "Method": "PutEpisode",
    "RelativePath": "api/Episodes/{id}",
    "HttpMethod": "PUT",
    "IsController": true,
    "Order": 0,
    "Parameters": [
      {
        "Name": "id",
        "Type": "System.Int32",
        "IsRequired": true
      },
      {
        "Name": "request",
        "Type": "API.DTOs.Episode.EpisodeUpdationRequest",
        "IsRequired": true
      }
    ],
    "ReturnTypes": [
      {
        "Type": "API.DTOs.APIresponse\u00601[[API.DTOs.Episode.EpisodeGeneralReponse, API, Version=1.0.0.0, Culture=neutral, PublicKeyToken=null]]",
        "MediaTypes": [
          "text/plain",
          "application/json",
          "text/json"
        ],
        "StatusCode": 200
      }
    ]
  },
  {
    "ContainingType": "API.Controllers.EpisodesController",
    "Method": "DeleteEpisode",
    "RelativePath": "api/Episodes/{id}",
    "HttpMethod": "DELETE",
    "IsController": true,
    "Order": 0,
    "Parameters": [
      {
        "Name": "id",
        "Type": "System.Int32",
        "IsRequired": true
      }
    ],
    "ReturnTypes": [
      {
        "Type": "API.DTOs.APIresponse\u00601[[System.String, System.Private.CoreLib, Version=8.0.0.0, Culture=neutral, PublicKeyToken=7cec85d7bea7798e]]",
        "MediaTypes": [
          "text/plain",
          "application/json",
          "text/json"
        ],
        "StatusCode": 200
      }
    ]
  },
  {
    "ContainingType": "API.Controllers.EpisodesController",
    "Method": "AddEpisodeToSeason",
    "RelativePath": "api/Episodes/{idEpisode}/season/{seasonId}",
    "HttpMethod": "PUT",
    "IsController": true,
    "Order": 0,
    "Parameters": [
      {
        "Name": "idEpisode",
        "Type": "System.Int32",
        "IsRequired": true
      },
      {
        "Name": "seasonId",
        "Type": "System.Int32",
        "IsRequired": true
      }
    ],
    "ReturnTypes": [
      {
        "Type": "API.DTOs.APIresponse\u00601[[API.DTOs.Episode.EpisodeGeneralReponse, API, Version=1.0.0.0, Culture=neutral, PublicKeyToken=null]]",
        "MediaTypes": [
          "text/plain",
          "application/json",
          "text/json"
        ],
        "StatusCode": 200
      }
    ]
  },
  {
    "ContainingType": "API.Controllers.EpisodesController",
    "Method": "RemoveEpisodeFromSeason",
    "RelativePath": "api/Episodes/{idEpisode}/season/{seasonId}/remove",
    "HttpMethod": "PUT",
    "IsController": true,
    "Order": 0,
    "Parameters": [
      {
        "Name": "idEpisode",
        "Type": "System.Int32",
        "IsRequired": true
      },
      {
        "Name": "seasonId",
        "Type": "System.Int32",
        "IsRequired": true
      }
    ],
    "ReturnTypes": [
      {
        "Type": "API.DTOs.APIresponse\u00601[[System.String, System.Private.CoreLib, Version=8.0.0.0, Culture=neutral, PublicKeyToken=7cec85d7bea7798e]]",
        "MediaTypes": [
          "text/plain",
          "application/json",
          "text/json"
        ],
        "StatusCode": 200
      }
    ]
  },
  {
    "ContainingType": "API.Controllers.EpisodesController",
    "Method": "GetEpisodesBySeasonId",
    "RelativePath": "api/Episodes/season/{id}",
    "HttpMethod": "GET",
    "IsController": true,
    "Order": 0,
    "Parameters": [
      {
        "Name": "id",
        "Type": "System.Int32",
        "IsRequired": true
      },
      {
        "Name": "Search",
        "Type": "System.String",
        "IsRequired": false
      },
      {
        "Name": "Page",
        "Type": "System.Int32",
        "IsRequired": false
      },
      {
        "Name": "PageSize",
        "Type": "System.Int32",
        "IsRequired": false
      },
      {
        "Name": "SortBy",
        "Type": "System.String",
        "IsRequired": false
      },
      {
        "Name": "IsAscending",
        "Type": "System.Boolean",
        "IsRequired": false
      },
      {
        "Name": "genere",
        "Type": "System.Nullable\u00601[[System.Int32, System.Private.CoreLib, Version=8.0.0.0, Culture=neutral, PublicKeyToken=7cec85d7bea7798e]]",
        "IsRequired": false
      }
    ],
    "ReturnTypes": [
      {
        "Type": "API.DTOs.APIresponse\u00601[[System.Collections.Generic.IEnumerable\u00601[[API.DTOs.Episode.EpisodeGeneralReponse, API, Version=1.0.0.0, Culture=neutral, PublicKeyToken=null]], System.Private.CoreLib, Version=8.0.0.0, Culture=neutral, PublicKeyToken=7cec85d7bea7798e]]",
        "MediaTypes": [
          "text/plain",
          "application/json",
          "text/json"
        ],
        "StatusCode": 200
      }
    ]
  },
  {
    "ContainingType": "API.Controllers.GenereController",
    "Method": "GetAllGeneres",
    "RelativePath": "api/generes/getAll",
    "HttpMethod": "GET",
    "IsController": true,
    "Order": 0,
    "Parameters": [],
    "ReturnTypes": [
      {
        "Type": "API.DTOs.APIresponse\u00601[[System.Collections.Generic.List\u00601[[API.Models.Genere, API, Version=1.0.0.0, Culture=neutral, PublicKeyToken=null]], System.Private.CoreLib, Version=8.0.0.0, Culture=neutral, PublicKeyToken=7cec85d7bea7798e]]",
        "MediaTypes": [
          "text/plain",
          "application/json",
          "text/json"
        ],
        "StatusCode": 200
      }
    ]
  },
  {
    "ContainingType": "API.Controllers.ImagesController",
    "Method": "Get",
    "RelativePath": "api/images/{path}",
    "HttpMethod": "GET",
    "IsController": true,
    "Order": 0,
    "Parameters": [
      {
        "Name": "path",
        "Type": "System.String",
        "IsRequired": true
      }
    ],
    "ReturnTypes": []
  },
  {
    "ContainingType": "API.Controllers.ImagesController",
    "Method": "GetAvatar",
    "RelativePath": "api/images/avatar/{path}",
    "HttpMethod": "GET",
    "IsController": true,
    "Order": 0,
    "Parameters": [
      {
        "Name": "path",
        "Type": "System.String",
        "IsRequired": true
      }
    ],
    "ReturnTypes": []
  },
  {
    "ContainingType": "API.Controllers.MoviesController",
    "Method": "PostMovie",
    "RelativePath": "api/movies",
    "HttpMethod": "POST",
    "IsController": true,
    "Order": 0,
    "Parameters": [
      {
        "Name": "request",
        "Type": "API.DTOs.Movies.MovieCreationRequest",
        "IsRequired": true
      }
    ],
    "ReturnTypes": [
      {
        "Type": "API.DTOs.APIresponse\u00601[[API.DTOs.Movies.MovieGeneralInformationReponse, API, Version=1.0.0.0, Culture=neutral, PublicKeyToken=null]]",
        "MediaTypes": [
          "text/plain",
          "application/json",
          "text/json"
        ],
        "StatusCode": 200
      }
    ]
  },
  {
    "ContainingType": "API.Controllers.MoviesController",
    "Method": "GetMovie",
    "RelativePath": "api/movies/{id}",
    "HttpMethod": "GET",
    "IsController": true,
    "Order": 0,
    "Parameters": [
      {
        "Name": "id",
        "Type": "System.Int32",
        "IsRequired": true
      }
    ],
    "ReturnTypes": [
      {
        "Type": "API.DTOs.APIresponse\u00601[[API.DTOs.Movies.MovieDetailInformation, API, Version=1.0.0.0, Culture=neutral, PublicKeyToken=null]]",
        "MediaTypes": [
          "text/plain",
          "application/json",
          "text/json"
        ],
        "StatusCode": 200
      }
    ]
  },
  {
    "ContainingType": "API.Controllers.MoviesController",
    "Method": "PutMovie",
    "RelativePath": "api/movies/{id}",
    "HttpMethod": "PUT",
    "IsController": true,
    "Order": 0,
    "Parameters": [
      {
        "Name": "id",
        "Type": "System.Int32",
        "IsRequired": true
      },
      {
        "Name": "request",
        "Type": "API.DTOs.Movies.MovieUpdationRequest",
        "IsRequired": true
      }
    ],
    "ReturnTypes": [
      {
        "Type": "API.DTOs.APIresponse\u00601[[API.DTOs.Movies.MovieGeneralInformationReponse, API, Version=1.0.0.0, Culture=neutral, PublicKeyToken=null]]",
        "MediaTypes": [
          "text/plain",
          "application/json",
          "text/json"
        ],
        "StatusCode": 200
      }
    ]
  },
  {
    "ContainingType": "API.Controllers.MoviesController",
    "Method": "DeleteMovie",
    "RelativePath": "api/movies/{id}",
    "HttpMethod": "DELETE",
    "IsController": true,
    "Order": 0,
    "Parameters": [
      {
        "Name": "id",
        "Type": "System.Int32",
        "IsRequired": true
      }
    ],
    "ReturnTypes": []
  },
  {
    "ContainingType": "API.Controllers.MoviesController",
    "Method": "DiscoverMovies",
    "RelativePath": "api/movies/discover",
    "HttpMethod": "GET",
    "IsController": true,
    "Order": 0,
    "Parameters": [],
    "ReturnTypes": [
      {
        "Type": "API.DTOs.APIresponse\u00601[[System.Collections.Generic.IEnumerable\u00601[[API.Models.Movie, API, Version=1.0.0.0, Culture=neutral, PublicKeyToken=null]], System.Private.CoreLib, Version=8.0.0.0, Culture=neutral, PublicKeyToken=7cec85d7bea7798e]]",
        "MediaTypes": [
          "text/plain",
          "application/json",
          "text/json"
        ],
        "StatusCode": 200
      }
    ]
  },
  {
    "ContainingType": "API.Controllers.MoviesController",
    "Method": "GetRandomMovies",
    "RelativePath": "api/movies/getRandom",
    "HttpMethod": "GET",
    "IsController": true,
    "Order": 0,
    "Parameters": [],
    "ReturnTypes": [
      {
        "Type": "API.DTOs.APIresponse\u00601[[System.Collections.Generic.IEnumerable\u00601[[API.DTOs.Movies.MovieGeneralInformationReponse, API, Version=1.0.0.0, Culture=neutral, PublicKeyToken=null]], System.Private.CoreLib, Version=8.0.0.0, Culture=neutral, PublicKeyToken=7cec85d7bea7798e]]",
        "MediaTypes": [
          "text/plain",
          "application/json",
          "text/json"
        ],
        "StatusCode": 200
      }
    ]
  },
  {
    "ContainingType": "API.Controllers.MoviesController",
    "Method": "GetMovies",
    "RelativePath": "api/movies/search",
    "HttpMethod": "GET",
    "IsController": true,
    "Order": 0,
    "Parameters": [
      {
        "Name": "Search",
        "Type": "System.String",
        "IsRequired": false
      },
      {
        "Name": "Page",
        "Type": "System.Int32",
        "IsRequired": false
      },
      {
        "Name": "PageSize",
        "Type": "System.Int32",
        "IsRequired": false
      },
      {
        "Name": "SortBy",
        "Type": "System.String",
        "IsRequired": false
      },
      {
        "Name": "IsAscending",
        "Type": "System.Boolean",
        "IsRequired": false
      },
      {
        "Name": "genere",
        "Type": "System.Nullable\u00601[[System.Int32, System.Private.CoreLib, Version=8.0.0.0, Culture=neutral, PublicKeyToken=7cec85d7bea7798e]]",
        "IsRequired": false
      }
    ],
    "ReturnTypes": [
      {
        "Type": "API.DTOs.APIresponse\u00601[[System.Collections.Generic.IEnumerable\u00601[[API.DTOs.Movies.MovieGeneralInformationReponse, API, Version=1.0.0.0, Culture=neutral, PublicKeyToken=null]], System.Private.CoreLib, Version=8.0.0.0, Culture=neutral, PublicKeyToken=7cec85d7bea7798e]]",
        "MediaTypes": [
          "text/plain",
          "application/json",
          "text/json"
        ],
        "StatusCode": 200
      }
    ]
  },
  {
    "ContainingType": "API.Controllers.SeasonsController",
    "Method": "PostSeason",
    "RelativePath": "api/seasons",
    "HttpMethod": "POST",
    "IsController": true,
    "Order": 0,
    "Parameters": [
      {
        "Name": "request",
        "Type": "API.DTOs.Season.SeasonCreationRequest",
        "IsRequired": true
      }
    ],
    "ReturnTypes": [
      {
        "Type": "API.DTOs.APIresponse\u00601[[API.DTOs.Season.SeasonGeneralInformation, API, Version=1.0.0.0, Culture=neutral, PublicKeyToken=null]]",
        "MediaTypes": [
          "text/plain",
          "application/json",
          "text/json"
        ],
        "StatusCode": 200
      }
    ]
  },
  {
    "ContainingType": "API.Controllers.SeasonsController",
    "Method": "GetSeason",
    "RelativePath": "api/seasons/{id}",
    "HttpMethod": "GET",
    "IsController": true,
    "Order": 0,
    "Parameters": [
      {
        "Name": "id",
        "Type": "System.Int32",
        "IsRequired": true
      }
    ],
    "ReturnTypes": [
      {
        "Type": "API.DTOs.APIresponse\u00601[[API.DTOs.Season.SeasonGeneralInformation, API, Version=1.0.0.0, Culture=neutral, PublicKeyToken=null]]",
        "MediaTypes": [
          "text/plain",
          "application/json",
          "text/json"
        ],
        "StatusCode": 200
      }
    ]
  },
  {
    "ContainingType": "API.Controllers.SeasonsController",
    "Method": "PutSeason",
    "RelativePath": "api/seasons/{id}",
    "HttpMethod": "PUT",
    "IsController": true,
    "Order": 0,
    "Parameters": [
      {
        "Name": "id",
        "Type": "System.Int32",
        "IsRequired": true
      },
      {
        "Name": "request",
        "Type": "API.DTOs.Season.SeasonUpdationRequest",
        "IsRequired": true
      }
    ],
    "ReturnTypes": [
      {
        "Type": "API.DTOs.APIresponse\u00601[[API.DTOs.Season.SeasonGeneralInformation, API, Version=1.0.0.0, Culture=neutral, PublicKeyToken=null]]",
        "MediaTypes": [
          "text/plain",
          "application/json",
          "text/json"
        ],
        "StatusCode": 200
      }
    ]
  },
  {
    "ContainingType": "API.Controllers.SeasonsController",
    "Method": "DeleteSeason",
    "RelativePath": "api/seasons/{id}",
    "HttpMethod": "DELETE",
    "IsController": true,
    "Order": 0,
    "Parameters": [
      {
        "Name": "id",
        "Type": "System.Int32",
        "IsRequired": true
      }
    ],
    "ReturnTypes": []
  },
  {
    "ContainingType": "API.Controllers.SeasonsController",
    "Method": "AddSeasonToMovie",
    "RelativePath": "api/seasons/add-to-movie/{movieId}/{idSeason}",
    "HttpMethod": "PUT",
    "IsController": true,
    "Order": 0,
    "Parameters": [
      {
        "Name": "movieId",
        "Type": "System.Int32",
        "IsRequired": true
      },
      {
        "Name": "idSeason",
        "Type": "System.Int32",
        "IsRequired": true
      }
    ],
    "ReturnTypes": [
      {
        "Type": "API.DTOs.APIresponse\u00601[[System.String, System.Private.CoreLib, Version=8.0.0.0, Culture=neutral, PublicKeyToken=7cec85d7bea7798e]]",
        "MediaTypes": [
          "text/plain",
          "application/json",
          "text/json"
        ],
        "StatusCode": 200
      }
    ]
  },
  {
    "ContainingType": "API.Controllers.SeasonsController",
    "Method": "GetSeasonsByMoiveId",
    "RelativePath": "api/seasons/getSeasonsByMoiveId/{id}",
    "HttpMethod": "GET",
    "IsController": true,
    "Order": 0,
    "Parameters": [
      {
        "Name": "id",
        "Type": "System.Int32",
        "IsRequired": true
      }
    ],
    "ReturnTypes": [
      {
        "Type": "API.DTOs.APIresponse\u00601[[System.Collections.Generic.List\u00601[[API.DTOs.Season.SeasonGeneralInformation, API, Version=1.0.0.0, Culture=neutral, PublicKeyToken=null]], System.Private.CoreLib, Version=8.0.0.0, Culture=neutral, PublicKeyToken=7cec85d7bea7798e]]",
        "MediaTypes": [
          "text/plain",
          "application/json",
          "text/json"
        ],
        "StatusCode": 200
      }
    ]
  },
  {
    "ContainingType": "API.Controllers.SeasonsController",
    "Method": "RemoveSeasonFromMovie",
    "RelativePath": "api/seasons/remove-from-movie/{movieId}/{idSeason}",
    "HttpMethod": "PUT",
    "IsController": true,
    "Order": 0,
    "Parameters": [
      {
        "Name": "movieId",
        "Type": "System.Int32",
        "IsRequired": true
      },
      {
        "Name": "idSeason",
        "Type": "System.Int32",
        "IsRequired": true
      }
    ],
    "ReturnTypes": [
      {
        "Type": "API.DTOs.APIresponse\u00601[[System.String, System.Private.CoreLib, Version=8.0.0.0, Culture=neutral, PublicKeyToken=7cec85d7bea7798e]]",
        "MediaTypes": [
          "text/plain",
          "application/json",
          "text/json"
        ],
        "StatusCode": 200
      }
    ]
  },
  {
    "ContainingType": "API.Controllers.UsersController",
    "Method": "GetUsers",
    "RelativePath": "api/users",
    "HttpMethod": "GET",
    "IsController": true,
    "Order": 0,
    "Parameters": [],
    "ReturnTypes": [
      {
        "Type": "System.Collections.Generic.IEnumerable\u00601[[API.DTOs.Users.UserGlobalReponse, API, Version=1.0.0.0, Culture=neutral, PublicKeyToken=null]]",
        "MediaTypes": [
          "text/plain",
          "application/json",
          "text/json"
        ],
        "StatusCode": 200
      }
    ]
  },
  {
    "ContainingType": "API.Controllers.UsersController",
    "Method": "CreateUser",
    "RelativePath": "api/users",
    "HttpMethod": "POST",
    "IsController": true,
    "Order": 0,
    "Parameters": [
      {
        "Name": "request",
        "Type": "API.DTOs.Users.UserCreationRequest",
        "IsRequired": true
      }
    ],
    "ReturnTypes": [
      {
        "Type": "API.DTOs.APIresponse\u00601[[API.DTOs.Users.UserGlobalReponse, API, Version=1.0.0.0, Culture=neutral, PublicKeyToken=null]]",
        "MediaTypes": [
          "text/plain",
          "application/json",
          "text/json"
        ],
        "StatusCode": 200
      }
    ]
  },
  {
    "ContainingType": "API.Controllers.UsersController",
    "Method": "GetUser",
    "RelativePath": "api/users/{id}",
    "HttpMethod": "GET",
    "IsController": true,
    "Order": 0,
    "Parameters": [
      {
        "Name": "id",
        "Type": "System.String",
        "IsRequired": true
      }
    ],
    "ReturnTypes": [
      {
        "Type": "API.DTOs.Users.UserGlobalReponse",
        "MediaTypes": [
          "text/plain",
          "application/json",
          "text/json"
        ],
        "StatusCode": 200
      }
    ]
  },
  {
    "ContainingType": "API.Controllers.UsersController",
    "Method": "UpdateUser",
    "RelativePath": "api/users/{id}",
    "HttpMethod": "PUT",
    "IsController": true,
    "Order": 0,
    "Parameters": [
      {
        "Name": "id",
        "Type": "System.String",
        "IsRequired": true
      },
      {
        "Name": "Username",
        "Type": "System.String",
        "IsRequired": false
      },
      {
        "Name": "Name",
        "Type": "System.String",
        "IsRequired": false
      },
      {
        "Name": "Age",
        "Type": "System.Nullable\u00601[[System.Int32, System.Private.CoreLib, Version=8.0.0.0, Culture=neutral, PublicKeyToken=7cec85d7bea7798e]]",
        "IsRequired": false
      },
      {
        "Name": "Email",
        "Type": "System.String",
        "IsRequired": false
      },
      {
        "Name": "DoB",
        "Type": "System.Nullable\u00601[[System.DateTime, System.Private.CoreLib, Version=8.0.0.0, Culture=neutral, PublicKeyToken=7cec85d7bea7798e]]",
        "IsRequired": false
      },
      {
        "Name": "PhoneNumber",
        "Type": "System.String",
        "IsRequired": false
      },
      {
        "Name": "Address",
        "Type": "System.String",
        "IsRequired": false
      },
      {
        "Name": "Avatar",
        "Type": "Microsoft.AspNetCore.Http.IFormFile",
        "IsRequired": false
      }
    ],
    "ReturnTypes": [
      {
        "Type": "API.DTOs.Users.UserGlobalReponse",
        "MediaTypes": [
          "text/plain",
          "application/json",
          "text/json"
        ],
        "StatusCode": 200
      }
    ]
  },
  {
    "ContainingType": "API.Controllers.UsersController",
    "Method": "DeleteUser",
    "RelativePath": "api/users/{id}",
    "HttpMethod": "DELETE",
    "IsController": true,
    "Order": 0,
    "Parameters": [
      {
        "Name": "id",
        "Type": "System.String",
        "IsRequired": true
      }
    ],
    "ReturnTypes": [
      {
        "Type": "API.DTOs.APIresponse\u00601[[System.String, System.Private.CoreLib, Version=8.0.0.0, Culture=neutral, PublicKeyToken=7cec85d7bea7798e]]",
        "MediaTypes": [
          "text/plain",
          "application/json",
          "text/json"
        ],
        "StatusCode": 200
      }
    ]
  },
  {
    "ContainingType": "API.Controllers.UsersController",
    "Method": "AddMovieFavorite",
    "RelativePath": "api/users/add-favorite-movie/{movieId}",
    "HttpMethod": "POST",
    "IsController": true,
    "Order": 0,
    "Parameters": [
      {
        "Name": "movieId",
        "Type": "System.Int32",
        "IsRequired": true
      }
    ],
    "ReturnTypes": [
      {
        "Type": "System.Void",
        "MediaTypes": [],
        "StatusCode": 200
      }
    ]
  },
  {
    "ContainingType": "API.Controllers.UsersController",
    "Method": "CheckFavoriteMovie",
    "RelativePath": "api/users/checkFavorite/{movieId}",
    "HttpMethod": "POST",
    "IsController": true,
    "Order": 0,
    "Parameters": [
      {
        "Name": "movieId",
        "Type": "System.Int32",
        "IsRequired": true
      }
    ],
    "ReturnTypes": [
      {
        "Type": "API.DTOs.APIresponse\u00601[[System.Boolean, System.Private.CoreLib, Version=8.0.0.0, Culture=neutral, PublicKeyToken=7cec85d7bea7798e]]",
        "MediaTypes": [
          "text/plain",
          "application/json",
          "text/json"
        ],
        "StatusCode": 200
      }
    ]
  },
  {
    "ContainingType": "API.Controllers.UsersController",
    "Method": "GetFavoriteMovies",
    "RelativePath": "api/users/get-favorite-movies",
    "HttpMethod": "GET",
    "IsController": true,
    "Order": 0,
    "Parameters": [],
    "ReturnTypes": [
      {
        "Type": "API.DTOs.APIresponse\u00601[[System.Collections.Generic.List\u00601[[API.DTOs.Movies.MovieGeneralInformationReponse, API, Version=1.0.0.0, Culture=neutral, PublicKeyToken=null]], System.Private.CoreLib, Version=8.0.0.0, Culture=neutral, PublicKeyToken=7cec85d7bea7798e]]",
        "MediaTypes": [
          "text/plain",
          "application/json",
          "text/json"
        ],
        "StatusCode": 200
      }
    ]
  },
  {
    "ContainingType": "API.Controllers.UsersController",
    "Method": "GetMyProfile",
    "RelativePath": "api/users/get-my-profile",
    "HttpMethod": "GET",
    "IsController": true,
    "Order": 0,
    "Parameters": [],
    "ReturnTypes": [
      {
        "Type": "API.DTOs.APIresponse\u00601[[API.DTOs.Users.UserGlobalReponse, API, Version=1.0.0.0, Culture=neutral, PublicKeyToken=null]]",
        "MediaTypes": [
          "text/plain",
          "application/json",
          "text/json"
        ],
        "StatusCode": 200
      }
    ]
  },
  {
    "ContainingType": "API.Controllers.UsersController",
    "Method": "RemoveFavoriteMovie",
    "RelativePath": "api/users/remove-favorite-movie/{movieId}",
    "HttpMethod": "POST",
    "IsController": true,
    "Order": 0,
    "Parameters": [
      {
        "Name": "movieId",
        "Type": "System.Int32",
        "IsRequired": true
      }
    ],
    "ReturnTypes": [
      {
        "Type": "System.Void",
        "MediaTypes": [],
        "StatusCode": 200
      }
    ]
  },
  {
    "ContainingType": "API.Controllers.UsersController",
    "Method": "UpdateMyProfile",
    "RelativePath": "api/users/update-my-profile",
    "HttpMethod": "PUT",
    "IsController": true,
    "Order": 0,
    "Parameters": [
      {
        "Name": "Username",
        "Type": "System.String",
        "IsRequired": false
      },
      {
        "Name": "Name",
        "Type": "System.String",
        "IsRequired": false
      },
      {
        "Name": "Age",
        "Type": "System.Nullable\u00601[[System.Int32, System.Private.CoreLib, Version=8.0.0.0, Culture=neutral, PublicKeyToken=7cec85d7bea7798e]]",
        "IsRequired": false
      },
      {
        "Name": "Email",
        "Type": "System.String",
        "IsRequired": false
      },
      {
        "Name": "DoB",
        "Type": "System.Nullable\u00601[[System.DateTime, System.Private.CoreLib, Version=8.0.0.0, Culture=neutral, PublicKeyToken=7cec85d7bea7798e]]",
        "IsRequired": false
      },
      {
        "Name": "PhoneNumber",
        "Type": "System.String",
        "IsRequired": false
      },
      {
        "Name": "Address",
        "Type": "System.String",
        "IsRequired": false
      },
      {
        "Name": "Avatar",
        "Type": "Microsoft.AspNetCore.Http.IFormFile",
        "IsRequired": false
      }
    ],
    "ReturnTypes": [
      {
        "Type": "API.DTOs.APIresponse\u00601[[System.String, System.Private.CoreLib, Version=8.0.0.0, Culture=neutral, PublicKeyToken=7cec85d7bea7798e]]",
        "MediaTypes": [
          "text/plain",
          "application/json",
          "text/json"
        ],
        "StatusCode": 200
      }
    ]
  },
  {
    "ContainingType": "API.Controllers.UsersController",
    "Method": "UpdateUserScreenTime",
    "RelativePath": "api/users/update-screen-time",
    "HttpMethod": "POST",
    "IsController": true,
    "Order": 0,
    "Parameters": [
      {
        "Name": "screenTime",
        "Type": "API.DTOs.Users.ScreenTime",
        "IsRequired": true
      }
    ],
    "ReturnTypes": []
  },
  {
    "ContainingType": "API.Controllers.VideosController",
    "Method": "PostVideo",
    "RelativePath": "api/videos",
    "HttpMethod": "POST",
    "IsController": true,
    "Order": 0,
    "Parameters": [
      {
        "Name": "request",
        "Type": "API.DTOs.Video.VideoCreationRequest",
        "IsRequired": true
      }
    ],
    "ReturnTypes": [
      {
        "Type": "API.DTOs.APIresponse\u00601[[API.Models.Video, API, Version=1.0.0.0, Culture=neutral, PublicKeyToken=null]]",
        "MediaTypes": [
          "text/plain",
          "application/json",
          "text/json"
        ],
        "StatusCode": 200
      }
    ]
  },
  {
    "ContainingType": "API.Controllers.VideosController",
    "Method": "GetVideo",
    "RelativePath": "api/videos/{code}",
    "HttpMethod": "GET",
    "IsController": true,
    "Order": 0,
    "Parameters": [
      {
        "Name": "code",
        "Type": "System.String",
        "IsRequired": true
      }
    ],
    "ReturnTypes": []
  },
  {
    "ContainingType": "API.Controllers.VideosController",
    "Method": "GetVideoHLS",
    "RelativePath": "api/videos/{code}/{fileName}",
    "HttpMethod": "GET",
    "IsController": true,
    "Order": 0,
    "Parameters": [
      {
        "Name": "code",
        "Type": "System.String",
        "IsRequired": true
      },
      {
        "Name": "fileName",
        "Type": "System.String",
        "IsRequired": true
      }
    ],
    "ReturnTypes": []
  },
  {
    "ContainingType": "API.Controllers.VideosController",
    "Method": "PutVideo",
    "RelativePath": "api/videos/{id}",
    "HttpMethod": "PUT",
    "IsController": true,
    "Order": 0,
    "Parameters": [
      {
        "Name": "id",
        "Type": "System.Int32",
        "IsRequired": true
      },
      {
        "Name": "request",
        "Type": "API.DTOs.Video.VideoUpdationRequest",
        "IsRequired": true
      }
    ],
    "ReturnTypes": [
      {
        "Type": "API.DTOs.APIresponse\u00601[[API.Models.Video, API, Version=1.0.0.0, Culture=neutral, PublicKeyToken=null]]",
        "MediaTypes": [
          "text/plain",
          "application/json",
          "text/json"
        ],
        "StatusCode": 200
      }
    ]
  },
  {
    "ContainingType": "API.Controllers.VideosController",
    "Method": "DeleteVideo",
    "RelativePath": "api/videos/{id}",
    "HttpMethod": "DELETE",
    "IsController": true,
    "Order": 0,
    "Parameters": [
      {
        "Name": "id",
        "Type": "System.Int32",
        "IsRequired": true
      }
    ],
    "ReturnTypes": []
  },
  {
    "ContainingType": "API.Controllers.TestController",
    "Method": "Index",
    "RelativePath": "test",
    "HttpMethod": "GET",
    "IsController": true,
    "Order": 0,
    "Parameters": [],
    "ReturnTypes": []
  }
]